mcp_axe/__init__.py
mcp_axe/__main__.py
mcp_axe/core.py
mcp_axe/server.py
mcp_axe-0.1.6.dist-info/licenses/LICENSE
mcp_axe-0.1.6.dist-info/METADATA
mcp_axe-0.1.6.dist-info/WHEEL
mcp_axe-0.1.6.dist-info/entry_points.txt
mcp_axe-0.1.6.dist-info/top_level.txt
mcp_axe-0.1.6.dist-info/RECORD
