Metadata-Version: 2.4
Name: mcp-axe
Version: 0.1.6
Summary: MCP plugin for accessibility testing using Axe-core
Author: Manoj Kumar
Author-email: your-email@example.com
License: MIT License
Requires-Python: >=3.8
License-File: LICENSE
Requires-Dist: typer>=0.15.2
Requires-Dist: uuid
Requires-Dist: fastapi>=0.115.12
Requires-Dist: uvicorn[standard]>=0.34.2
Requires-Dist: selenium>=4.31.0
Requires-Dist: playwright>=1.51.0
Requires-Dist: pyyaml>=6.0.2
Requires-Dist: toml>=0.10.2
Requires-Dist: requests>=2.32.3
Requires-Dist: mcp>=1.6.0
Provides-Extra: dev
Requires-Dist: build; extra == "dev"
Requires-Dist: twine; extra == "dev"
Requires-Dist: pytest-asyncio; extra == "dev"
Requires-Dist: pytest>=8.3.5; extra == "dev"
Requires-Dist: pytest-asyncio>=0.26.0; extra == "dev"
Requires-Dist: pytest-cov>=6.1.1; extra == "dev"
Requires-Dist: pytest-httpx>=0.35.0; extra == "dev"
Requires-Dist: pytest-playwright>=0.7.0; extra == "dev"
Requires-Dist: httpx>=0.28.1; extra == "dev"
Requires-Dist: sseclient-py>=1.8.0; extra == "dev"
Requires-Dist: flake8>=7.2.0; extra == "dev"
Requires-Dist: black>=25.1.0; extra == "dev"
Requires-Dist: isort>=6.0.1; extra == "dev"
Requires-Dist: mypy>=1.15.0; extra == "dev"
Requires-Dist: pre-commit>=4.2.0; extra == "dev"
Dynamic: author-email
Dynamic: license-file
Dynamic: requires-python
